{
	"ng": 23719652,
	"an": 22634268,
	"ia": 11273626,
	"sh": 10022356,
	"ji": 9756605,
	"zh": 9381833,
	"en": 9150318,
	"in": 8762975,
	"hi": 7260719,
	"he": 7016658,
	"hu": 6966624,
	"ao": 6523177,
	"xi": 6394669,
	"on": 6203243,
	"ua": 5597556,
	"ai": 5484983,
	"de": 5151985,
	"ha": 5120090,
	"yi": 4534641,
	"ou": 4391781,
	"uo": 4368529,
	"ch": 4279423,
	"ei": 3753301,
	"ho": 3395185,
	"li": 3381841,
	"da": 3359213,
	"gu": 3349600,
	"yu": 3073345,
	"qi": 3060973,
	"ui": 2966137,
	"we": 2218661,
	"i,": 2143478,
	"di": 2107441,
	"yo": 2099960,
	"fa": 2099614,
	"du": 1790436,
	"ya": 1723703,
	"ie": 1692704,
	"n,": 1651757,
	"za": 1597879,
	"ba": 1577241,
	"bu": 1569452,
	"bi": 1549374,
	"go": 1515396,
	"qu": 1511870,
	"re": 1488245,
	"ge": 1476154,
	"mi": 1430016,
	"ti": 1408984,
	"g,": 1361564,
	"un": 1357071,
	"iu": 1352647,
	"me": 1343364,
	"ta": 1338923,
	"zu": 1335907,
	"ue": 1331787,
	"ga": 1185591,
	"wa": 1173599,
	"ju": 1168085,
	"xu": 1163387,
	"ye": 1150622,
	"u,": 1115067,
	"ni": 1107538,
	"to": 1071494,
	"le": 1068912,
	"fe": 1025839,
	"zi": 1009465,
	"fu": 934317,
	"wu": 931279,
	"la": 900650,
	"pi": 871254,
	"do": 849121,
	"be": 842463,
	"ka": 822840,
	"su": 799255,
	"ke": 741561,
	"ne": 733124,
	"o,": 729847,
	"e,": 689990,
	"er": 681350,
	"i.": 653052,
	"lu": 647776,
	"ca": 630145,
	"si": 609725,
	"tu": 606940,
	"ru": 568936,
	"ku": 568936,
	"n.": 557954,
	"ma": 539996,
	"na": 536404,
	"wo": 521203,
	"g.": 506132,
	"ze": 466292,
	"ci": 453470,
	"sa": 437957,
	"ri": 412224,
	"a,": 406506,
	"ra": 366731,
	"mu": 364364,
	"pa": 359406,
	"zo": 353568,
	"u.": 343694,
	"ko": 304938,
	"ce": 289164,
	"cu": 279749,
	"e.": 268438,
	"ro": 248114,
	"o.": 228963,
	"co": 227493,
	"mo": 205852,
	"te": 198395,
	"pe": 188443,
	"bo": 165509,
	"no": 152420,
	"a.": 124607,
	"',": 118162,
	"se": 115771,
	"lo": 110168,
	"po": 105357,
	"so": 98170,
	"pu": 90678,
	"nu": 68375,
	"'.": 60661,
	"io": 59663,
	"fo": 47776,
	"r,": 27487,
	",z": 26930,
	",'": 23760,
	",y": 21723,
	",j": 18676,
	"ar": 16347,
	",s": 16188,
	",d": 15829,
	"'z": 15449,
	",b": 14160,
	"'s": 12003,
	"at": 10991,
	"al": 10534,
	"or": 10185,
	",t": 9876,
	"nt": 9451,
	"es": 9451,
	",q": 9412,
	",c": 9350,
	",g": 9261,
	"st": 9259,
	"'w": 8943,
	"'y": 8760,
	",x": 8301,
	"os": 8131,
	"oo": 7979,
	"ac": 7957,
	"nd": 7916,
	",w": 7518,
	"th": 7487,
	"el": 7300,
	"ic": 7288,
	"'g": 7265,
	"ec": 7242,
	"'d": 7212,
	"'j": 7203,
	"it": 6993,
	"ed": 6821,
	",h": 6435,
	"'x": 6417,
	"is": 6313,
	"ct": 6286,
	"nn": 6273,
	",l": 6213,
	"ad": 6139,
	"il": 6098,
	"ll": 5993,
	"),": 5988,
	"cl": 5967,
	"as": 5819,
	"..": 5508,
	"om": 5456,
	"ve": 5323,
	"et": 4931,
	"n/": 4913,
	"'h": 4887,
	"--": 4885,
	"og": 4762,
	",m": 4693,
	"am": 4597,
	"rt": 4540,
	",f": 4502,
	"ol": 4491,
	"'b": 4448,
	"r.": 4382,
	",r": 4324,
	",e": 4322,
	"od": 4256,
	"'c": 4127,
	"'t": 4121,
	"'l": 4075,
	"ay": 4067,
	"nc": 4058,
	"wi": 4047,
	"ea": 4028,
	"ph": 4022,
	"vi": 4009,
	"ur": 3981,
	"t-": 3968,
	"eb": 3841,
	"id": 3833,
	"'m": 3826,
	"(s": 3745,
	"ok": 3639,
	"ry": 3632,
	"ss": 3631,
	"gl": 3536,
	"ww": 3515,
	",n": 3457,
	"tr": 3451,
	"'q": 3450,
	")d": 3420,
	"ow": 3393,
	"us": 3242,
	"ns": 3223,
	"ag": 3116,
	"va": 3078,
	"ig": 3069,
	",k": 3036,
	"'n": 3020,
	"ep": 2985,
	"ir": 2972,
	"rd": 2953,
	"rs": 2943,
	"ee": 2881,
	"cc": 2860,
	"ey": 2830,
	"ld": 2816,
	"op": 2777,
	")z": 2768,
	"fi": 2766,
	"'r": 2746,
	"em": 2715,
	"of": 2702,
	"ck": 2702,
	"pr": 2637,
	"'f": 2603,
	"ot": 2551,
	"pd": 2535,
	"im": 2528,
	"ty": 2520,
	"tt": 2476,
	".c": 2464,
	"d,": 2413,
	"rn": 2378,
	"bl": 2350,
	"(y": 2344,
	")j": 2334,
	"pt": 2288,
	"gh": 2282,
	"ap": 2264,
	"(e": 2247,
	"s)": 2235,
	"d-": 2234,
	"iv": 2224,
	"n)": 2213,
	"ab": 2199,
	"-z": 2168,
	"e)": 2157,
	"jo": 2145,
	"sc": 2140,
	"w.": 2117,
	"ob": 2087,
	"ut": 2086,
	"n;": 2072,
	".'": 2038,
	"rl": 2031,
	"oc": 2029,
	"az": 2021,
	"gr": 2008,
	"ul": 2000,
	"'k": 1998,
	"ks": 1996,
	"pl": 1982,
	"ex": 1975,
	"au": 1948,
	"rk": 1939,
	"dr": 1936,
	"sp": 1929,
	")y": 1927,
	"av": 1922,
	"i;": 1905,
	")s": 1901,
	").": 1897,
	"mm": 1871,
	"ov": 1861,
	"ki": 1828,
	"ew": 1815,
	"fr": 1811,
	"ts": 1809,
	"br": 1801,
	";s": 1783,
	";z": 1737,
	"pp": 1722,
	"sd": 1722,
	"rr": 1710,
	"s,": 1705,
	"dd": 1703,
	"rg": 1702,
	"cr": 1682,
	",p": 1656,
	"a)": 1637,
	"rc": 1608,
	"ht": 1600,
	"aj": 1589,
	"gt": 1589,
	"gi": 1567,
	"by": 1556,
	"lt": 1537,
	";d": 1529,
	"dy": 1521,
	"if": 1516,
	"ev": 1514,
	";y": 1509,
	"ja": 1506,
	"ub": 1505,
	"eg": 1496,
	"t,": 1492,
	"ny": 1482,
	"nk": 1482,
	"ly": 1482,
	"pz": 1473,
	"ah": 1473,
	"m,": 1469,
	"ws": 1463,
	";t": 1462,
	"up": 1461,
	".j": 1444,
	";j": 1438,
	"g;": 1396,
	"iz": 1385,
	"ds": 1372,
	"oi": 1359,
	"ak": 1350,
	"c,": 1340,
	"r)": 1330,
	"uc": 1313,
	"oh": 1301,
	".d": 1289,
	"ax": 1262,
	"ip": 1256,
	"py": 1252,
	"um": 1243,
	"y,": 1238,
	")h": 1234,
	"mp": 1228,
	"ff": 1228,
	"-s": 1225,
	"k)": 1221,
	".g": 1214,
	"-j": 1211,
	"c.": 1206,
	"y)": 1185,
	"my": 1168,
	"-y": 1154,
	"i/": 1150,
	"s-": 1144,
	"sy": 1140,
	"t)": 1135,
	"dj": 1135,
	"gs": 1124,
	"d.": 1109,
	"rv": 1103,
	"rm": 1100,
	"ys": 1077,
	"ls": 1076,
	"p,": 1065,
	"hn": 1059,
	"cs": 1057,
	"ps": 1057,
	",a": 1044,
	"u;": 1042,
	"mb": 1021,
	"oy": 1020,
	"eo": 1017,
	"ud": 1013,
	"ib": 1004,
	"e-": 1004,
	"ez": 999,
	"l.": 999,
	"'p": 995,
	";g": 995,
	"ik": 993,
	"l,": 981,
	";c": 980,
	"cn": 975,
	"cd": 956,
	";q": 956,
	"sk": 955,
	"tc": 955,
	")b": 954,
	"yr": 954,
	"b,": 943,
	"vy": 939,
	".z": 931,
	"oz": 912,
	"d)": 909,
	"-d": 907,
	"ox": 893,
	"gy": 891,
	"ky": 886,
	"s.": 883,
	"sm": 883,
	"cy": 877,
	"aw": 872,
	"ef": 869,
	"tw": 869,
	"hr": 863,
	")g": 862,
	"td": 849,
	"je": 848,
	"(w": 844,
	"oa": 841,
	"rp": 828,
	"dz": 828,
	")x": 827,
	"k,": 822,
	"'a": 820,
	"g/": 820,
	"ft": 819,
	"-b": 816,
	"vo": 813,
	"-t": 813,
	"yd": 811,
	"c)": 805,
	"i)": 802,
	"yt": 801,
	"af": 797,
	"rb": 789,
	"-g": 783,
	".s": 781,
	"o)": 777,
	")c": 766,
	"fl": 765,
	"-c": 765,
	"l)": 762,
	"tz": 759,
	"nl": 757,
	"e;": 757,
	"ms": 753,
	"-'": 751,
	".y": 726,
	"o;": 718,
	"dl": 718,
	"eh": 714,
	"ug": 706,
	"v.": 704,
	";x": 704,
	";l": 702,
	"v,": 700,
	"-x": 696,
	"dg": 687,
	"ae": 685,
	"-w": 671,
	"sl": 665,
	"ej": 662,
	"-m": 661,
	"gd": 659,
	"-h": 658,
	";w": 656,
	"cz": 656,
	"sz": 652,
	"m.": 651,
	"p)": 651,
	"p.": 649,
	"u/": 637,
	"ix": 634,
	"i-": 633,
	"g)": 631,
	"aq": 629,
	"mc": 627,
	"bs": 625,
	"gg": 619,
	"'(": 619,
	"nz": 614,
	"c-": 613,
	"eu": 609,
	")f": 608,
	";'": 607,
	"hz": 603,
	"hy": 603,
	"yn": 597,
	"wj": 594,
	"m)": 592,
	"(l": 592,
	"iy": 591,
	")t": 591,
	"-l": 587,
	"t.": 584,
	"pc": 584,
	"dc": 580,
	"''": 577,
	"nf": 575,
	"jb": 567,
	"sj": 566,
	"ek": 565,
	";h": 564,
	"e/": 560,
	";e": 558,
	"uk": 556,
	"cm": 546,
	"md": 542,
	"ij": 541,
	";b": 541,
	"tl": 539,
	")'": 538,
	"/,": 536,
	"oe": 533,
	"kd": 533,
	")q": 531,
	",,": 529,
	"lm": 526,
	"lk": 525,
	"x-": 522,
	"sw": 518,
	".x": 514,
	"sb": 514,
	"n-": 513,
	")l": 511,
	"pb": 510,
	")w": 509,
	"-q": 509,
	"dh": 505,
	"tm": 504,
	"yl": 496,
	"k-": 495,
	"nb": 494,
	"aa": 493,
	".h": 492,
	"a-": 491,
	"bd": 490,
	"f-": 487,
	"l-": 485,
	"nj": 481,
	"iw": 480,
	"tn": 477,
	"wh": 477,
	"e'": 474,
	".q": 471,
	"gw": 464,
	"dm": 462,
	"'e": 462,
	"gz": 461,
	"lb": 459,
	"bb": 457,
	";f": 456,
	"dw": 452,
	"r-": 451,
	"oj": 449,
	"dx": 449,
	"lv": 447,
	"pm": 446,
	"db": 444,
	"lc": 443,
	".b": 441,
	"lf": 440,
	"ux": 439,
	";n": 435,
	"yp": 434,
	"cj": 433,
	"wn": 431,
	"nh": 431,
	"ym": 428,
	";r": 428,
	"(z": 421,
	")r": 418,
	"sg": 416,
	"(q": 416,
	"tj": 411,
	"(j": 411,
	"h.": 408,
	"mg": 406,
	"pg": 405,
	".w": 401,
	"b.": 400,
	"xx": 400,
	"a/": 400,
	"nm": 397,
	"vd": 396,
	"gj": 395,
	"nv": 390,
	",(": 389,
	"h)": 388,
	"km": 384,
	"kh": 384,
	";m": 380,
	"tf": 377,
	"lz": 376,
	"-f": 375,
	")n": 375,
	"b-": 374,
	"rz": 374,
	"gn": 372,
	"pj": 372,
	"a;": 368,
	"h,": 367,
	"tg": 366,
	"cp": 363,
	"kl": 362,
	"(b": 361,
	".t": 360,
	"sx": 360,
	"xp": 356,
	"gb": 355,
	"n'": 354,
	"tx": 354,
	"-n": 353,
	"hd": 350,
	"yb": 349,
	"-r": 348,
	"bj": 348,
	"o/": 347,
	"h-": 343,
	"mj": 343,
	"ih": 341,
	"mz": 340,
	"rf": 339,
	"dt": 337,
	"f,": 331,
	"sn": 330,
	"tb": 330,
	".n": 325,
	"cg": 322,
	"x,": 320,
	"ml": 319,
	"eq": 317,
	"hl": 315,
	"w)": 314,
	")k": 312,
	"gm": 311,
	"kz": 308,
	"y.": 307,
	"xt": 306,
	"o-": 302,
	"k.": 301,
	"y-": 301,
	"w,": 300,
	"hm": 299,
	"yc": 295,
	"nr": 294,
	"dp": 292,
	"yz": 291,
	"sf": 290,
	"g-": 288,
	"lg": 288,
	"yy": 287,
	"px": 286,
	"kr": 285,
	".l": 285,
	"xz": 284,
	"rh": 284,
	"tp": 284,
	"cx": 283,
	"ii": 281,
	"q,": 280,
	"j.": 280,
	"vs": 277,
	"(x": 277,
	"rj": 272,
	"lj": 271,
	"kg": 271,
	"b)": 271,
	".f": 270,
	"bc": 267,
	"';": 265,
	"f)": 265,
	"sq": 265,
	"m-": 264,
	"p-": 264,
	"hs": 264,
	"xy": 264,
	"pv": 263,
	"xc": 260,
	"bp": 260,
	"cf": 259,
	"uf": 258,
	"u)": 257,
	"xa": 256,
	"r'": 255,
	"dn": 255,
	"uz": 252,
	"a'": 249,
	"y'": 249,
	",.": 245,
	"wd": 241,
	"nw": 240,
	"vc": 239,
	"bz": 239,
	"lp": 238,
	"pw": 238,
	"fd": 235,
	"qq": 235,
	"(d": 234,
	"//": 231,
	"-p": 229,
	"rw": 228,
	"d'": 227,
	".m": 226,
	"lh": 226,
	"-k": 226,
	"cq": 225,
	"cw": 224,
	"cb": 224,
	"vz": 224,
	"fz": 223,
	")m": 222,
	"nx": 222,
	"yj": 217,
	"kj": 216,
	"uy": 216,
	"v-": 215,
	"hh": 215,
	"bx": 215,
	"dv": 214,
	"yx": 214,
	"(g": 214,
	");": 213,
	"gc": 212,
	"xe": 211,
	"gx": 211,
	"zz": 208,
	"iq": 207,
	"s'": 206,
	".,": 206,
	"pn": 206,
	"kb": 205,
	"gf": 203,
	"fj": 201,
	"kw": 201,
	".r": 200,
	"l'": 196,
	";k": 195,
	"m/": 195,
	"bg": 195,
	"df": 194,
	"s/": 193,
	"sr": 192,
	"dq": 191,
	"-a": 189,
	"oq": 189,
	"uj": 188,
	"mh": 188,
	"a(": 186,
	"bh": 186,
	"hw": 186,
	"kc": 186,
	"xj": 184,
	"-i": 184,
	"z,": 183,
	"yh": 183,
	"o'": 182,
	"vj": 181,
	"uh": 180,
	"hg": 180,
	"z)": 179,
	"t'": 179,
	"xg": 178,
	".k": 178,
	"kn": 176,
	"mx": 174,
	"xd": 171,
	"zd": 167,
	"f.": 167,
	"u-": 166,
	"fs": 165,
	"-e": 165,
	"pk": 163,
	"mt": 162,
	"zy": 161,
	"/.": 159,
	")p": 157,
	"yw": 155,
	"yg": 151,
	"rx": 151,
	"j-": 151,
	"mr": 150,
	"p/": 150,
	";p": 148,
	"b/": 147,
	"e(": 147,
	"v)": 147,
	"s(": 146,
	"kt": 145,
	"lw": 145,
	"xs": 144,
	";/": 143,
	"tk": 143,
	",o": 143,
	"q.": 142,
	"fy": 142,
	"wr": 142,
	"vb": 140,
	"(t": 139,
	"tq": 139,
	"(h": 138,
	"hf": 137,
	"dk": 136,
	"wy": 135,
	"mk": 134,
	"x)": 133,
	"xb": 132,
	"gp": 132,
	"yf": 130,
	",i": 130,
	"qd": 130,
	"lx": 129,
	"gk": 128,
	"pf": 128,
	"mw": 126,
	"c/": 123,
	"bt": 123,
	"wl": 123,
	"vl": 122,
	"g'": 122,
	"(c": 120,
	"i'": 120,
	"np": 117,
	"nq": 117,
	"(m": 117,
	"kk": 116,
	"mn": 116,
	"vh": 116,
	"o(": 116,
	"kx": 116,
	"t(": 110,
	"ln": 110,
	"'o": 110,
	"bq": 110,
	"x.": 109,
	";(": 108,
	"hj": 108,
	"(f": 107,
	"mf": 105,
	"sv": 104,
	"qz": 103,
	".p": 102,
	"r/": 100,
	"hk": 100,
	"wf": 100,
	"c'": 100,
	"hb": 98,
	"fq": 98,
	"bw": 96,
	")(": 96,
	"r(": 95,
	"c(": 95,
	"h'": 94,
	"kf": 94,
	"i(": 94,
	"hc": 93,
	"fg": 93,
	"')": 92,
	"w-": 92,
	"d/": 89,
	";a": 88,
	"bm": 88,
	"x'": 88,
	"xo": 87,
	"yk": 87,
	"fc": 85,
	"n(": 85,
	"xh": 85,
	"vx": 85,
	"t/": 84,
	"rq": 84,
	"p(": 82,
	"-o": 82,
	")a": 82,
	"g(": 80,
	"d(": 80,
	"vg": 80,
	"qc": 79,
	"m'": 77,
	"bf": 76,
	"q-": 76,
	"gq": 76,
	"tv": 76,
	"p;": 75,
	"lr": 74,
	"k'": 74,
	"p'": 72,
	"xw": 72,
	"j,": 72,
	"kp": 72,
	"jr": 72,
	"qs": 71,
	"yq": 71,
	"=,": 71,
	"zk": 71,
	"vt": 70,
	"y(": 69,
	")e": 69,
	"uw": 68,
	"wt": 68,
	"(k": 68,
	"zb": 67,
	"qy": 67,
	"vr": 66,
	"uv": 66,
	"wx": 66,
	"f/": 65,
	"fh": 65,
	"zs": 65,
	"qh": 65,
	"fb": 63,
	"fx": 63,
	"fm": 63,
	"vp": 62,
	"m(": 61,
	"z.": 61,
	"u'": 61,
	"mq": 61,
	"hp": 60,
	"xf": 60,
	"lq": 60,
	".a": 60,
	"vn": 58,
	"z-": 58,
	"zg": 57,
	"wc": 57,
	"kv": 57,
	"wg": 57,
	"jh": 56,
	"wz": 56,
	"hx": 54,
	"jj": 54,
	"('": 54,
	"vu": 54,
	"pq": 54,
	"bn": 53,
	"bk": 52,
	"l(": 50,
	"wb": 50,
	"l/": 50,
	"js": 49,
	"jy": 49,
	"vk": 49,
	"zw": 49,
	";,": 48,
	"jd": 48,
	"wk": 47,
	"kq": 47,
	"zm": 47,
	"=d": 47,
	"-)": 47,
	")-": 46,
	"(n": 46,
	"(p": 46,
	"(r": 46,
	"vw": 45,
	"qa": 45,
	"-.": 45,
	"x(": 44,
	"wm": 44,
	"xm": 42,
	"jz": 42,
	"u(": 42,
	"qb": 41,
	"xn": 41,
	"jx": 41,
	"v'": 40,
	"zn": 40,
	"uq": 40,
	"zp": 40,
	"xl": 39,
	";.": 39,
	"zj": 38,
	"(a": 38,
	"m;": 38,
	"yv": 38,
	"=z": 38,
	"==": 38,
	"zl": 37,
	"vq": 37,
	"k(": 37,
	"b(": 37,
	"w'": 36,
	"zc": 36,
	"b'": 34,
	"?z": 34,
	"qj": 34,
	"fn": 33,
	"fw": 33,
	"hq": 33,
	".o": 32,
	"vf": 32,
	"fk": 32,
	"vm": 32,
	"ql": 32,
	"w/": 32,
	"qw": 32,
	"-,": 32,
	"jp": 32,
	",-": 31,
	"/s": 31,
	"qx": 31,
	"wq": 31,
	"qt": 30,
	"uu": 30,
	"jl": 29,
	"zx": 29,
	"/h": 29,
	"/b": 29,
	"zt": 29,
	"'-": 28,
	"w(": 27,
	"qk": 27,
	"s;": 27,
	"xq": 27,
	"/'": 27,
	"xr": 27,
	"=j": 26,
	"/d": 26,
	"mv": 26,
	"-v": 25,
	"j)": 25,
	"],": 25,
	"h(": 24,
	"-u": 24,
	"zr": 24,
	"fp": 24,
	"qm": 24,
	"k/": 24,
	"zf": 23,
	"=s": 23,
	"`w": 23,
	"jm": 23,
	"qg": 23,
	"/m": 22,
	"q)": 22,
	"v/": 22,
	"jc": 22,
	"jk": 22,
	"=-": 21,
	"f'": 21,
	"f(": 20,
	"e=": 20,
	"xk": 20,
	"wp": 20,
	";o": 20,
	"qo": 20,
	"=h": 19,
	"`y": 19,
	"qr": 19,
	"v(": 18,
	"jg": 18,
	",/": 18,
	"t;": 18,
	"jw": 17,
	"'i": 17,
	"`z": 17,
	"=x": 17,
	"?y": 17,
	"=.": 17,
	"q'": 17,
	".-": 16,
	"hv": 16,
	"r;": 16,
	"j/": 16,
	"?t": 16,
	"(i": 16,
	"`.": 16,
	"`x": 16,
	"jt": 16,
	".)": 15,
	".e": 15,
	"?s": 15,
	"`h": 15,
	"qp": 15,
	"z/": 14,
	"h/": 14,
	"?d": 14,
	"`q": 14,
	"))": 13,
	"jn": 13,
	"?j": 12,
	"`s": 12,
	"y/": 12,
	"='": 12,
	"'/": 12,
	"=l": 11,
	"qn": 11,
	"qf": 11,
	"`n": 11,
	"/c": 11,
	"k;": 10,
	"].": 10,
	"?w": 10,
	".i": 10,
	"=y": 10,
	"=f": 10,
	"`l": 10,
	"-(": 9,
	"?e": 9,
	"l;": 9,
	"xv": 9,
	"=/": 9,
	"=b": 9,
	"/y": 9,
	"/a": 9,
	"zq": 9,
	".(": 9,
	"=a": 9,
	"?h": 9,
	"bv": 9,
	"`j": 9,
	"t=": 9,
	"x/": 9,
	"?x": 9,
	"'v": 8,
	";-": 8,
	"`,": 8,
	"=n": 8,
	"d;": 8,
	"`t": 8,
	"?c": 8,
	"q/": 8,
	"y;": 8,
	"?l": 8,
	"z'": 8,
	"=q": 8,
	"=p": 8,
	",v": 8,
	"/z": 8,
	"j'": 7,
	"?b": 7,
	"v;": 7,
	"`g": 7,
	"vv": 7,
	"q(": 7,
	"c;": 7,
	"=g": 7,
	"`c": 7,
	"/l": 6,
	"=k": 6,
	"cv": 6,
	"/n": 6,
	"=c": 6,
	"gv": 6,
	"jf": 6,
	"w;": 6,
	"/g": 6,
	";;": 6,
	"d=": 6,
	"f;": 6,
	"?n": 6,
	"`b": 6,
	"`d": 6,
	",)": 6,
	"?'": 6,
	"/x": 5,
	"zv": 5,
	"l=": 5,
	"/j": 5,
	"?r": 5,
	"jq": 5,
	"=i": 5,
	"=m": 5,
	";i": 5,
	".;": 5,
	"q;": 5,
	"/k": 5,
	",;": 5,
	"-/": 4,
	"/w": 4,
	"p=": 4,
	"=t": 4,
	"n`": 4,
	")?": 4,
	")i": 4,
	"/f": 4,
	"/i": 4,
	"'u": 4,
	"/p": 4,
	"`a": 4,
	"/r": 4,
	"z(": 4,
	"fv": 4,
	"j(": 4,
	"?g": 4,
	"`'": 4,
	"(o": 4,
	"`k": 4,
	"=)": 3,
	"?q": 3,
	"``": 3,
	"b;": 3,
	"?m": 3,
	")o": 3,
	"]/": 3,
	"/o": 3,
	")/": 3,
	"=w": 3,
	"=v": 3,
	"/q": 3,
	"s=": 3,
	"`-": 3,
	"/t": 3,
	",u": 2,
	"i?": 2,
	"q=": 2,
	"./": 2,
	"?a": 2,
	".u": 2,
	"x;": 2,
	"x=": 2,
	"qe": 2,
	"(.": 2,
	"a=": 2,
	"r=": 2,
	")v": 2,
	"];": 2,
	";u": 2,
	"qv": 2,
	"i`": 2,
	"g=": 2,
	"?.": 2,
	"t?": 2,
	"n=": 2,
	"m=": 2,
	"?k": 2,
	"=r": 2,
	"/e": 2,
	"/(": 1,
	"/;": 1,
	"y=": 1,
	";)": 1,
	"[/": 1,
	"h=": 1,
	"=u": 1,
	"t`": 1,
	"v=": 1,
	"=e": 1,
	"/v": 1,
	"(v": 1,
	"z=": 1,
	"`f": 1,
	"`)": 1,
	"\\,": 1,
	"-;": 1,
	"=;": 1,
	"c=": 1,
	"/-": 1,
	"`o": 1,
	"d?": 1,
	"=`": 1,
	"(u": 1,
	"wv": 1,
	"a?": 1,
	"r?": 1,
	"f=": 1,
	"=o": 1,
	"p?": 1,
	"j;": 1,
	"?f": 1,
	"=(": 1,
	"`e": 1,
	"k=": 1
}