{
	"th": 43687,
	"he": 34905,
	"in": 28185,
	"an": 23963,
	"er": 21785,
	"ou": 21752,
	"re": 20546,
	"on": 16830,
	"nd": 16654,
	"at": 15657,
	"ha": 15104,
	"ng": 14441,
	"to": 13784,
	"en": 13736,
	"it": 13532,
	"or": 12979,
	"ve": 12703,
	"es": 12146,
	"st": 11853,
	"yo": 11757,
	"is": 11689,
	"me": 11528,
	"ar": 11370,
	"hi": 10365,
	"ea": 10093,
	"se": 9925,
	"al": 9894,
	"ll": 9851,
	"te": 9850,
	"ed": 9502,
	"le": 9455,
	"ne": 9226,
	"of": 9005,
	"ti": 8800,
	"as": 8482,
	"li": 8212,
	"be": 8106,
	"no": 8064,
	"nt": 7794,
	"ur": 6892,
	"wh": 6841,
	"om": 6779,
	"ho": 6752,
	"ro": 6746,
	"de": 6738,
	"ow": 6647,
	"wa": 6598,
	"ut": 6379,
	"el": 6348,
	"co": 6307,
	"ri": 6199,
	"ma": 6194,
	"ca": 6022,
	"ee": 5925,
	"ot": 5916,
	"us": 5905,
	"et": 5812,
	"we": 5728,
	"so": 5724,
	"lo": 5391,
	"ce": 5376,
	"il": 5173,
	"wi": 5133,
	"pe": 5026,
	"fo": 4931,
	"ch": 4923,
	"ta": 4901,
	"ke": 4876,
	"ra": 4794,
	"do": 4767,
	"e.": 4712,
	"ay": 4665,
	"un": 4539,
	"ly": 4510,
	"ic": 4400,
	"ev": 4377,
	"rs": 4369,
	"ac": 4316,
	"si": 4285,
	"ld": 4226,
	"ge": 4206,
	"io": 4167,
	"la": 4132,
	"gh": 4088,
	"oo": 3965,
	"mo": 3944,
	"e,": 3942,
	"ad": 3925,
	"ul": 3913,
	"ns": 3881,
	"wo": 3839,
	"im": 3818,
	"ec": 3790,
	"tr": 3785,
	"di": 3765,
	"'s": 3716,
	"em": 3674,
	"if": 3615,
	"ie": 3574,
	"sh": 3515,
	"ai": 3510,
	"s.": 3472,
	"ry": 3447,
	"fe": 3447,
	"ss": 3408,
	"s,": 3383,
	"ig": 3380,
	"id": 3271,
	"go": 3263,
	"rt": 3216,
	"ir": 3214,
	"bu": 3214,
	"av": 3181,
	"n'": 3174,
	"am": 3095,
	"ol": 3057,
	"mi": 3010,
	"os": 3003,
	"ni": 2936,
	"ey": 2934,
	"pl": 2903,
	"nc": 2892,
	"bo": 2885,
	"my": 2875,
	"fi": 2866,
	"ct": 2837,
	"'t": 2824,
	"pr": 2797,
	"ht": 2783,
	"ts": 2722,
	"sa": 2699,
	"iv": 2685,
	"po": 2632,
	"pa": 2542,
	"op": 2475,
	"na": 2426,
	"t.": 2422,
	"su": 2422,
	"ab": 2396,
	"bl": 2375,
	"ak": 2353,
	"tt": 2275,
	"fr": 2258,
	"od": 2245,
	"kn": 2210,
	"ov": 2153,
	"da": 2149,
	"ck": 2135,
	"tu": 2117,
	"rd": 2069,
	"t,": 2057,
	"t'": 2057,
	"fa": 2044,
	"vi": 2013,
	"ag": 2006,
	"i'": 2003,
	"ki": 1948,
	"ty": 1922,
	"d.": 1917,
	"ap": 1887,
	"y,": 1882,
	"n.": 1850,
	"d,": 1834,
	"ug": 1833,
	"ba": 1814,
	"up": 1788,
	"ds": 1753,
	"sp": 1741,
	"y.": 1728,
	"mp": 1723,
	"ei": 1709,
	"ci": 1706,
	"ny": 1695,
	"gr": 1691,
	"n,": 1667,
	"ru": 1666,
	"au": 1661,
	"gi": 1639,
	"rn": 1623,
	"ik": 1578,
	"r.": 1561,
	"ep": 1499,
	"e'": 1499,
	"ys": 1472,
	"ex": 1468,
	"cr": 1464,
	"ye": 1449,
	"uc": 1440,
	"pi": 1422,
	"pp": 1401,
	"ju": 1395,
	"ga": 1376,
	"ef": 1370,
	"eo": 1367,
	"ok": 1361,
	"br": 1340,
	"nk": 1338,
	"wn": 1317,
	"rl": 1303,
	"r,": 1292,
	"'r": 1278,
	"oi": 1257,
	"ia": 1257,
	"um": 1254,
	"tl": 1253,
	"dr": 1237,
	"ls": 1234,
	"rr": 1234,
	"cl": 1232,
	"mu": 1200,
	"ue": 1196,
	"by": 1195,
	"sc": 1195,
	"u'": 1190,
	"ff": 1186,
	"fu": 1132,
	"ew": 1092,
	"nn": 1092,
	"gs": 1085,
	"'m": 1077,
	"..": 1074,
	"qu": 1071,
	"bi": 1068,
	"oc": 1063,
	"rm": 1056,
	"g.": 1001,
	"nl": 994,
	"rk": 993,
	"ui": 973,
	"cu": 966,
	"aw": 921,
	"lu": 920,
	"ob": 917,
	"lf": 911,
	"ft": 900,
	"hu": 899,
	"pu": 894,
	"mb": 893,
	"lt": 891,
	"hr": 888,
	"ms": 880,
	"l,": 846,
	"dy": 839,
	"gu": 831,
	"ua": 830,
	"g,": 800,
	"'v": 784,
	"tw": 782,
	"va": 776,
	"fl": 769,
	"'l": 749,
	"l.": 735,
	"eg": 706,
	"hy": 700,
	"ib": 699,
	"oe": 696,
	"sk": 693,
	"du": 684,
	"rg": 680,
	"og": 676,
	"m.": 675,
	"ud": 656,
	"af": 653,
	"sl": 648,
	"ks": 644,
	"rc": 643,
	"pt": 636,
	"gl": 635,
	"sm": 628,
	"h,": 627,
	"ip": 615,
	"yt": 607,
	"mm": 595,
	"yi": 579,
	"ph": 577,
	"vo": 565,
	"sn": 559,
	"lk": 558,
	"ps": 553,
	"dn": 549,
	"oa": 540,
	"nu": 530,
	"iz": 528,
	"ze": 526,
	"w,": 518,
	"o,": 507,
	"m,": 505,
	"wr": 498,
	"h.": 495,
	"ws": 487,
	"ub": 479,
	"y'": 475,
	"u.": 461,
	"lw": 455,
	"cc": 451,
	"oy": 451,
	"jo": 448,
	"sw": 448,
	"xp": 447,
	"nf": 446,
	"dd": 444,
	"o.": 443,
	"tc": 442,
	"w.": 433,
	"rv": 421,
	"dl": 412,
	"'d": 404,
	"k,": 400,
	"sy": 397,
	"nv": 395,
	"rf": 389,
	"yb": 384,
	"k.": 377,
	"gn": 374,
	"u,": 354,
	"lv": 353,
	"rp": 325,
	"xt": 320,
	"bs": 318,
	"xi": 316,
	"eb": 301,
	"eh": 300,
	".\\": 298,
	"je": 298,
	"gg": 273,
	"ky": 260,
	"p.": 260,
	"oh": 259,
	"eq": 253,
	"dg": 251,
	"p,": 243,
	"uf": 242,
	"cy": 229,
	"lp": 226,
	"f.": 225,
	"uy": 222,
	"lm": 222,
	"xc": 221,
	"py": 216,
	"ek": 213,
	"az": 211,
	"ah": 200,
	"rb": 199,
	"ix": 197,
	"a.": 195,
	"ka": 195,
	"e-": 189,
	"f,": 180,
	"yp": 176,
	"ja": 175,
	"a,": 173,
	"xa": 173,
	"wl": 165,
	"e;": 164,
	"r'": 162,
	"rh": 162,
	"ym": 152,
	"dv": 152,
	"kl": 151,
	"bb": 147,
	"rw": 146,
	"gy": 143,
	"za": 143,
	"tm": 141,
	"eu": 138,
	"s;": 134,
	"sf": 134,
	"hs": 133,
	"nj": 132,
	"zi": 128,
	"y-": 127,
	"lr": 125,
	"cs": 124,
	"'c": 124,
	"ax": 123,
	"yw": 122,
	"ya": 122,
	"tn": 121,
	"d'": 121,
	"-s": 120,
	"xe": 119,
	"bj": 116,
	"ox": 113,
	"hn": 113,
	"iu": 111,
	"gt": 110,
	"mr": 108,
	"nm": 107,
	"d-": 106,
	"bt": 106,
	"t-": 105,
	",\\": 105,
	"o'": 105,
	"-t": 104,
	"c.": 99,
	"r-": 98,
	"-c": 92,
	"/\\": 91,
	"n-": 91,
	"yr": 90,
	"nh": 89,
	"zy": 88,
	"f-": 88,
	"mn": 87,
	"t;": 87,
	"lc": 85,
	"-f": 85,
	"yl": 81,
	"c,": 81,
	"-b": 78,
	"mf": 78,
	"yc": 77,
	"zz": 77,
	"hl": 77,
	"hm": 75,
	"fy": 74,
	"zo": 74,
	"dm": 74,
	"o-": 72,
	"uo": 72,
	"yn": 70,
	"-l": 68,
	"sq": 68,
	"d;": 67,
	"ez": 66,
	"nb": 66,
	"l-": 65,
	"h-": 64,
	"s'": 63,
	"dw": 63,
	"aj": 63,
	"i.": 62,
	"oz": 61,
	"'e": 61,
	"iq": 60,
	"y;": 60,
	"-p": 60,
	"nr": 59,
	"i,": 59,
	"-a": 59,
	"b.": 59,
	"sd": 59,
	"nq": 59,
	"-h": 58,
	"r;": 57,
	"-o": 57,
	"gm": 56,
	"-e": 56,
	"-d": 53,
	"vy": 53,
	"n;": 53,
	"'.": 52,
	"e\\": 52,
	"g-": 51,
	"-m": 51,
	"',": 51,
	"-r": 50,
	"ae": 50,
	"fs": 50,
	"-w": 49,
	"np": 49,
	"tf": 47,
	"-i": 45,
	"uk": 45,
	"g;": 44,
	"ko": 44,
	"ln": 42,
	"lb": 41,
	"a'": 40,
	"b,": 39,
	"ku": 39,
	"-g": 39,
	"hb": 39,
	"nw": 39,
	"ej": 39,
	"g'": 38,
	"wy": 38,
	"yd": 38,
	"dh": 36,
	"db": 36,
	"wd": 36,
	"hw": 35,
	"uz": 34,
	"uh": 34,
	"ji": 34,
	"i-": 34,
	"ao": 34,
	"xy": 33,
	"wf": 33,
	"sg": 33,
	"ml": 32,
	"pm": 32,
	"l;": 31,
	"l'": 31,
	"kw": 31,
	"zl": 30,
	"s\\": 30,
	"a-": 29,
	"y\\": 29,
	"bv": 29,
	"'a": 28,
	"n\\": 28,
	"tz": 28,
	"sb": 28,
	"wt": 28,
	"tb": 28,
	"m-": 27,
	"nx": 27,
	"x,": 27,
	"h;": 27,
	"'n": 26,
	"df": 26,
	"lg": 26,
	"-u": 26,
	"s-": 26,
	"x.": 25,
	"oj": 25,
	"p-": 24,
	"yg": 24,
	"ux": 24,
	"mt": 24,
	"xh": 24,
	"x-": 23,
	"cq": 23,
	"-n": 23,
	"'i": 23,
	".'": 23,
	"b-": 21,
	"m'": 21,
	"'b": 21,
	"w-": 21,
	"vu": 21,
	"kr": 21,
	"sr": 21,
	"xo": 20,
	"h'": 20,
	"p;": 20,
	"k-": 20,
	"gd": 19,
	"'h": 19,
	"w'": 19,
	"pk": 19,
	"t\\": 19,
	"m;": 19,
	"wb": 19,
	"kf": 19,
	"'f": 18,
	"xu": 18,
	"dc": 18,
	"hd": 18,
	"-k": 18,
	"bm": 18,
	"yf": 17,
	"k;": 17,
	"gf": 17,
	"l\\": 16,
	"mc": 16,
	"hf": 16,
	"'w": 15,
	"yz": 15,
	"td": 15,
	"bd": 14,
	"r\\": 14,
	"d\\": 14,
	"dt": 14,
	"dj": 14,
	"tp": 13,
	"v.": 13,
	"pw": 13,
	"'g": 13,
	",'": 12,
	"pb": 12,
	"-y": 12,
	"kb": 11,
	"'p": 11,
	"p'": 11,
	"'o": 11,
	"aq": 11,
	"uv": 11,
	"wk": 11,
	"nz": 11,
	"bn": 11,
	"kt": 11,
	"ih": 11,
	"pn": 11,
	"w;": 10,
	"c-": 10,
	"z,": 10,
	"qw": 10,
	"aa": 10,
	"c'": 9,
	"u\\": 9,
	"km": 9,
	"kh": 9,
	"dp": 9,
	"fw": 9,
	"v,": 9,
	"hq": 9,
	"kp": 8,
	"dk": 8,
	"z.": 8,
	"pc": 8,
	"bw": 8,
	"pf": 8,
	"wu": 8,
	"rq": 8,
	"zh": 7,
	"hp": 7,
	"/'": 7,
	"vs": 7,
	"lh": 7,
	".e": 7,
	"-j": 7,
	"oq": 7,
	".a": 7,
	"k'": 7,
	"o;": 7,
	"zt": 7,
	"p\\": 7,
	"gw": 7,
	"-v": 6,
	".,": 6,
	"u-": 6,
	"a;": 6,
	"uj": 6,
	"cn": 6,
	"u;": 6,
	"f\\": 6,
	"hh": 6,
	"wm": 6,
	"-x": 6,
	"iw": 6,
	"f'": 5,
	"'u": 5,
	"-q": 5,
	"yh": 5,
	"bc": 5,
	"kg": 5,
	"b'": 5,
	"r/": 5,
	"tg": 4,
	"k\\": 4,
	"rz": 4,
	"==": 4,
	"i\\": 4,
	"hc": 4,
	".w": 4,
	"ij": 4,
	"f;": 4,
	"ii": 4,
	";p": 4,
	"zu": 4,
	"/m": 4,
	"-,": 4,
	"xq": 4,
	"sv": 4,
	"uu": 4,
	"vl": 4,
	"yu": 4,
	"v'": 4,
	"kd": 4,
	"vv": 3,
	"'k": 3,
	"gx": 3,
	"zk": 3,
	"/o": 3,
	"bh": 3,
	"'y": 3,
	"a\\": 3,
	"m\\": 3,
	"mw": 3,
	".u": 3,
	"cz": 3,
	"wp": 3,
	"w\\": 3,
	"c\\": 3,
	".c": 3,
	"gb": 3,
	"z-": 3,
	"gk": 3,
	"/h": 3,
	"fn": 3,
	".r": 3,
	"zm": 3,
	"zs": 3,
	"cb": 3,
	"zv": 3,
	"/c": 2,
	"t/": 2,
	"fc": 2,
	"g\\": 2,
	"hz": 2,
	"hg": 2,
	"c;": 2,
	"p]": 2,
	"gp": 2,
	".m": 2,
	"fm": 2,
	"d/": 2,
	".s": 2,
	";f": 2,
	"yv": 2,
	"vh": 2,
	"].": 2,
	"mh": 2,
	"o\\": 2,
	";n": 2,
	"--": 2,
	"iy": 2,
	"vk": 2,
	"s/": 2,
	"vp": 2,
	"b;": 2,
	"zg": 2,
	"/.": 2,
	"m/": 2,
	"xf": 2,
	"'j": 2,
	"yy": 2,
	"fg": 2,
	";h": 2,
	"pd": 2,
	"pg": 2,
	"gz": 2,
	".g": 2,
	"q-": 2,
	"fd": 2,
	"xl": 2,
	"v-": 2,
	"xs": 2,
	";c": 2,
	"[b": 2,
	"x'": 2,
	"rj": 2,
	"mg": 1,
	".n": 1,
	"[d": 1,
	"/p": 1,
	"sj": 1,
	"o/": 1,
	";b": 1,
	".t": 1,
	"md": 1,
	"/y": 1,
	"l/": 1,
	"/s": 1,
	"yj": 1,
	"j\\": 1,
	"[p": 1,
	";\\": 1,
	"z'": 1,
	".f": 1,
	"bp": 1,
	"lz": 1,
	"-\\": 1,
	"gj": 1,
	"qr": 1,
	"'z": 1,
	"kk": 1,
	"z\\": 1,
	"/]": 1,
	"'/": 1,
	";r": 1,
	"k=": 1,
	"t]": 1,
	"kv": 1,
	"tk": 1,
	"vf": 1,
	"q,": 1,
	"qs": 1,
	"kj": 1,
	"[l": 1,
	"cd": 1,
	"dq": 1,
	"vb": 1,
	"xx": 1,
	".l": 1,
	"d]": 1,
	"l]": 1,
	"sz": 1,
	"cv": 1,
	"rx": 1,
	";d": 1,
	"[q": 1,
	"y]": 1,
	"m]": 1,
	"n/": 1,
	".b": 1,
	"g]": 1,
	"vr": 1,
	"hk": 1,
	"cf": 1,
	"wc": 1,
	"\\\\": 1,
	"[s": 1,
	"wg": 1,
	"-;": 1,
	"yk": 1,
	"='": 1,
	".p": 1,
	"uw": 1,
	"[v": 1,
	"x\\": 1,
	"\\n": 1,
	";o": 1,
	"h/": 1,
	";t": 1,
	"zw": 1,
	"e/": 1,
	"n]": 1,
	"']": 1,
	"jr": 1,
	"r]": 1,
	"j-": 1,
	"cp": 1,
	"[]": 1
}